CHANGES.txt
README.txt
setup.py
docs/INSTALL.txt
docs/LICENSE.GPL
docs/LICENSE.txt
pfg/__init__.py
pfg.drafts.egg-info/PKG-INFO
pfg.drafts.egg-info/SOURCES.txt
pfg.drafts.egg-info/dependency_links.txt
pfg.drafts.egg-info/entry_points.txt
pfg.drafts.egg-info/namespace_packages.txt
pfg.drafts.egg-info/not-zip-safe
pfg.drafts.egg-info/paster_plugins.txt
pfg.drafts.egg-info/requires.txt
pfg.drafts.egg-info/top_level.txt
pfg/drafts/__init__.py
pfg/drafts/browser.py
pfg/drafts/configure.zcml
pfg/drafts/tool.py
pfg/drafts/profiles/default/metadata.xml
pfg/drafts/profiles/default/skins.xml
pfg/drafts/profiles/default/toolset.xml
pfg/drafts/profiles/default/types/FormFolder.xml
pfg/drafts/skins/pfg_drafts/pfg_draft_macros.pt
pfg/drafts/skins/pfg_drafts/pfg_draft_validate.vpy
pfg/drafts/skins/pfg_drafts/pfg_draft_view.cpt
pfg/drafts/skins/pfg_drafts/pfg_draft_view.cpt.metadata
pfg/drafts/tests/__init__.py
pfg/drafts/tests/tests.py