Metadata-Version: 1.0
Name: pfg.drafts
Version: 1.0b1
Summary: Allows users to save drafts of PloneFormGen forms in progress
Home-page: http://svn.plone.org/svn/collective/pfg.drafts/trunk
Author: David Glick, Groundwire
Author-email: davidglick@groundwire.org
License: GPL
Keywords: ploneformgen form draft save
Platform: UNKNOWN
Classifier: Framework :: Plone
Classifier: Programming Language :: Python
